kahi_ciarp_works/Kahi_ciarp_works.py
kahi_ciarp_works/__init__.py
kahi_ciarp_works/_version.py
kahi_ciarp_works/parser.py
kahi_ciarp_works/process_one.py
Kahi_ciarp_works-0.1.0b0.dist-info/LICENSE
Kahi_ciarp_works-0.1.0b0.dist-info/METADATA
Kahi_ciarp_works-0.1.0b0.dist-info/WHEEL
Kahi_ciarp_works-0.1.0b0.dist-info/top_level.txt
Kahi_ciarp_works-0.1.0b0.dist-info/RECORD
