Metadata-Version: 2.2
Name: Kahi_ciarp_works
Version: 0.1.0b0
Summary: Kahi plugin to insert and update works from CIARP databases
Home-page: https://github.com/colav/Kahi_plugins
Author: Colav
Author-email: colav@udea.edu.co
License: BSD
License-File: LICENSE
Requires-Dist: kahi
Requires-Dist: pymongo
Requires-Dist: joblib
Requires-Dist: pandas
Requires-Dist: kahi_impactu_utils
Requires-Dist: mohan
Requires-Dist: iso639~=0.1.4
Dynamic: author
Dynamic: author-email
Dynamic: description
Dynamic: description-content-type
Dynamic: home-page
Dynamic: license
Dynamic: requires-dist
Dynamic: summary
